{"\u0435": 0, "\u044f": 1, "\u0438": 2, "n": 3, "\u0431": 5, "\u0430": 6, ")": 7, "\u043f": 8, "\u0436": 9, "\u00ab": 10, "i": 11, "r": 12, "\u043a": 13, "c": 14, "(": 15, "\u044b": 16, "\u2013": 17, "k": 18, "\u043c": 19, "\u043d": 20, "x": 21, "\u0451": 22, "g": 23, "\u0444": 24, "\u0447": 25, "\u0433": 26, "\u0446": 27, "\u044a": 28, "\u043e": 29, "\u0434": 30, "\u0448": 31, "p": 32, "\u043b": 33, "\u0449": 34, "z": 35, "f": 36, "\u0437": 37, "\u0443": 38, "t": 39, "\u0442": 40, "l": 41, "\u0439": 42, "\u2011": 43, "\u2026": 44, "\u00bb": 45, "m": 46, "\u2212": 47, "'": 48, "\u0432": 49, "e": 50, "\u044e": 51, "\u044c": 52, "o": 53, "a": 54, "\u0440": 55, "s": 56, "\u2014": 57, "\u0445": 58, "\u0441": 59, "b": 60, "h": 61, "\u044d": 62, "|": 4, "[UNK]": 63, "[PAD]": 64}